ChanzhongshuochanJiaoniChaogupiao/README.md
ChanzhongshuochanJiaoniChaogupiao/__init__.py
ChanzhongshuochanJiaoniChaogupiao/__main__.py
ChanzhongshuochanJiaoniChaogupiao/file.epub
ChanzhongshuochanJiaoniChaogupiao/index.html
ChanzhongshuochanJiaoniChaogupiao/css/__init__.py
ChanzhongshuochanJiaoniChaogupiao/css/annotations.css
ChanzhongshuochanJiaoniChaogupiao/css/main.css
ChanzhongshuochanJiaoniChaogupiao/css/normalize.css
ChanzhongshuochanJiaoniChaogupiao/css/popup.css
ChanzhongshuochanJiaoniChaogupiao/font/__init__.py
ChanzhongshuochanJiaoniChaogupiao/font/fontello.eot
ChanzhongshuochanJiaoniChaogupiao/font/fontello.svg
ChanzhongshuochanJiaoniChaogupiao/font/fontello.ttf
ChanzhongshuochanJiaoniChaogupiao/font/fontello.woff
ChanzhongshuochanJiaoniChaogupiao/img/__init__.py
ChanzhongshuochanJiaoniChaogupiao/img/annotator-glyph-sprite.png
ChanzhongshuochanJiaoniChaogupiao/img/annotator-icon-sprite.png
ChanzhongshuochanJiaoniChaogupiao/img/apple-touch-icon.png
ChanzhongshuochanJiaoniChaogupiao/img/cancelfullscreen.png
ChanzhongshuochanJiaoniChaogupiao/img/close.png
ChanzhongshuochanJiaoniChaogupiao/img/fullscreen.png
ChanzhongshuochanJiaoniChaogupiao/img/loader.gif
ChanzhongshuochanJiaoniChaogupiao/img/menu-icon.png
ChanzhongshuochanJiaoniChaogupiao/img/save.png
ChanzhongshuochanJiaoniChaogupiao/img/saved.png
ChanzhongshuochanJiaoniChaogupiao/img/settings-s.png
ChanzhongshuochanJiaoniChaogupiao/img/settings.png
ChanzhongshuochanJiaoniChaogupiao/img/star.png
ChanzhongshuochanJiaoniChaogupiao/js/__init__.py
ChanzhongshuochanJiaoniChaogupiao/js/epub.js
ChanzhongshuochanJiaoniChaogupiao/js/epub.min.js
ChanzhongshuochanJiaoniChaogupiao/js/epub.min.map
ChanzhongshuochanJiaoniChaogupiao/js/hooks.min.js
ChanzhongshuochanJiaoniChaogupiao/js/hooks.min.map
ChanzhongshuochanJiaoniChaogupiao/js/reader.js
ChanzhongshuochanJiaoniChaogupiao/js/reader.js.map
ChanzhongshuochanJiaoniChaogupiao/js/reader.min.js
ChanzhongshuochanJiaoniChaogupiao/js/reader.min.map
chanzhongshuochan_jiaoni_chaogupiao-2022.10.15.0.dist-info/METADATA
chanzhongshuochan_jiaoni_chaogupiao-2022.10.15.0.dist-info/WHEEL
chanzhongshuochan_jiaoni_chaogupiao-2022.10.15.0.dist-info/entry_points.txt
chanzhongshuochan_jiaoni_chaogupiao-2022.10.15.0.dist-info/top_level.txt
chanzhongshuochan_jiaoni_chaogupiao-2022.10.15.0.dist-info/RECORD
